basicmathematicsw/__init__.py
basicmathematicsw/operations.py
basicmathematicsw-0.1.0.dist-info/METADATA
basicmathematicsw-0.1.0.dist-info/WHEEL
basicmathematicsw-0.1.0.dist-info/top_level.txt
basicmathematicsw-0.1.0.dist-info/RECORD
