Metadata-Version: 2.1
Name: basicmathematicsw
Version: 0.1.0
Summary: A simple package with basic math functions
Home-page: https://github.com/yourusername/basicmathematicsw
Author: Your Name
Author-email: your.email@example.com
Classifier: Programming Language :: Python :: 3
Classifier: License :: OSI Approved :: MIT License
Classifier: Operating System :: OS Independent
Requires-Python: >=3.6
